expansion/__init__.py
expansion/callbacks.py
expansion/colors.py
expansion/expansion.py
expansion/utils.py
expansion_raj_csh-1.0.2.2.dist-info/LICENSE
expansion_raj_csh-1.0.2.2.dist-info/METADATA
expansion_raj_csh-1.0.2.2.dist-info/WHEEL
expansion_raj_csh-1.0.2.2.dist-info/top_level.txt
expansion_raj_csh-1.0.2.2.dist-info/RECORD
