Metadata-Version: 2.1
Name: expansion-raj-csh
Version: 1.0.2.2
Summary: A simple generative art project.
Home-page: https://github.com/Raj-CSH/expansion
Author: Rajarshi Mandal
Author-email: rajarshimandal22@gmail.com
License: UNKNOWN
Platform: UNKNOWN
Classifier: Programming Language :: Python :: 3
Classifier: License :: OSI Approved :: MIT License
Classifier: Operating System :: OS Independent
Requires-Python: >=3.6
Requires-Dist: numpy
Requires-Dist: opencv-python
Requires-Dist: pillow
Requires-Dist: pygame
